cassy/__init__.py
cassy/casdriv.py
cassy/cql.py
cassy/model.py
cassy-0.0.13.dist-info/LICENSE
cassy-0.0.13.dist-info/WHEEL
cassy-0.0.13.dist-info/METADATA
cassy-0.0.13.dist-info/RECORD
