Metadata-Version: 2.1
Name: cassy
Version: 0.0.13
Summary: Python Cassandra Database API
Home-page: https://github.com/tZ3ma/cassy
License: MIT
Keywords: cassandra,database,api
Author: Mathias Ammon
Author-email: mathias.ammon@tuhh.de
Requires-Python: >=3.8,<4.0
Classifier: License :: OSI Approved :: MIT License
Classifier: Programming Language :: Python :: 3
Classifier: Programming Language :: Python :: 3.10
Classifier: Programming Language :: Python :: 3.8
Classifier: Programming Language :: Python :: 3.9
Requires-Dist: cqlsh (>=6.0.1,<7.0.0)
Requires-Dist: requests (>=2.27.1,<3.0.0)
Project-URL: Repository, https://github.com/tZ3ma/cassy
